CHANGES.txt
LICENSE.txt
MANIFEST.in
README.txt
details
setup.py
Aesthete.egg-info/PKG-INFO
Aesthete.egg-info/SOURCES.txt
Aesthete.egg-info/dependency_links.txt
Aesthete.egg-info/requires.txt
Aesthete.egg-info/top_level.txt
aesthete/__init__.py
aesthete/aespythonconsole.py
aesthete/aesspreadsheet.py
aesthete/help_browser.py
aesthete/tablemaker.py
aesthete/glancer/Canvas.py
aesthete/glancer/Glancer.py
aesthete/glancer/Legend.py
aesthete/glancer/Line.py
aesthete/glancer/Pie.py
aesthete/glancer/Plot.py
aesthete/glancer/Plot3d.py
aesthete/glancer/Scatter.py
aesthete/glancer/__init__.py
aesthete/glosser/Containers.py
aesthete/glosser/Glancer.py
aesthete/glosser/Glosser.py
aesthete/glosser/GlosserWidget.py
aesthete/glosser/Glypher.py
aesthete/glosser/TextView.py
aesthete/glosser/__init__.py
aesthete/gluer/Gluer.py
aesthete/gluer/__init__.py
aesthete/glypher/Alternatives.py
aesthete/glypher/BinaryExpression.py
aesthete/glypher/Caret.py
aesthete/glypher/Commands.py
aesthete/glypher/ComplexPlane.py
aesthete/glypher/ConfigWidgets.py
aesthete/glypher/Decoration.py
aesthete/glypher/Dynamic.py
aesthete/glypher/Entity.py
aesthete/glypher/Fraction.py
aesthete/glypher/Function.py
aesthete/glypher/GlyphMaker.py
aesthete/glypher/GlypherView.py
aesthete/glypher/Interpret.py
aesthete/glypher/InterpretBackend.py
aesthete/glypher/Mirror.py
aesthete/glypher/Parser.py
aesthete/glypher/Phrase.py
aesthete/glypher/PhraseGroup.py
aesthete/glypher/Plot.py
aesthete/glypher/References.py
aesthete/glypher/Renderers.py
aesthete/glypher/Spacer.py
aesthete/glypher/Symbol.py
aesthete/glypher/Table.py
aesthete/glypher/Toolbox.py
aesthete/glypher/Widget.py
aesthete/glypher/Word.py
aesthete/glypher/__init__.py
aesthete/glypher/draw.py
aesthete/glypher/glypher.py
aesthete/glypher/gutils.py
aesthete/glypher/misc.py
aesthete/sources/CSV.py
aesthete/sources/Function.py
aesthete/sources/Source.py
aesthete/sources/VTK.py
aesthete/sources/__init__.py
aesthete/sources/sources.py
aesthete/third_party/__init__.py
aesthete/third_party/ipython_view.py
aesthete/third_party/ipython_view_10.py
aesthete/third_party/ipython_view_11.py
aobject/__init__.py
aobject/alogger.py
