Metadata-Version: 1.0
Name: Aesthete
Version: 0.4.2
Summary: Integrated mathematics environment
Home-page: http://launchpad.net/aesthete
Author: Phil Weir
Author-email: pweir@maths.otago.ac.nz
License: LICENSE.txt
Platform: UNKNOWN
Classifier: Programming Language :: Python
Classifier: Development Status :: 2 - Pre-Alpha
Classifier: Environment :: X11 Applications
Classifier: Environment :: X11 Applications :: GTK
Classifier: Intended Audience :: Science/Research
Classifier: Intended Audience :: Education
Classifier: Topic :: Scientific/Engineering :: Mathematics
